nice_logging/__init__.py
nice_logging/nice_logging.py
nice_logging/structured_logging.py
nice_logging-1.1.1.dist-info/LICENSE
nice_logging-1.1.1.dist-info/METADATA
nice_logging-1.1.1.dist-info/WHEEL
nice_logging-1.1.1.dist-info/top_level.txt
nice_logging-1.1.1.dist-info/RECORD
