Metadata-Version: 2.1
Name: nice_logging
Version: 1.1.1
Summary: Simple logging library with colored and timestamped output by default
Home-page: https://github.com/aib/nice_logging
Author: Orhan "aib" Kavrakoglu
Author-email: aibok42@gmail.com
License: MIT
Keywords: logging,logger,colored,style
Classifier: Intended Audience :: Developers
Classifier: Topic :: System :: Logging
Classifier: Programming Language :: Python :: 3
Classifier: License :: OSI Approved :: MIT License
Classifier: Operating System :: OS Independent
Requires-Python: >=3.2
License-File: LICENSE
